pushpull/__init__.py
pushpull/config.py
pushpull/linereader.py
pushpull/amqp/__init__.py
pushpull/amqp/auth.py
pushpull/amqp/client.py
pushpull/amqp/gateway.py
pushpull/amqp/gateway/__init__.py
pushpull/amqp/gateway/driver_aioamqp.py
pushpull/amqp/gateway/driver_asynqp.py
pushpull/amqp/gateway/driver_base.py
pushpull/amqp/rpc/__init__.py
pushpull/amqp/rpc/driver_aioamqp.py
pushpull/amqp/rpc/driver_base.py
pushpull/auth/__init__.py
pushpull/auth/django_oauth_toolkit.py
pushpull/auth/simple_file.py
pushpull/cli/__init__.py
pushpull/cli/client.py
pushpull/cli/server.py
pushpull/websocket/__init__.py
pushpull/websocket/auth.py
pushpull/websocket/client.py
pushpull/websocket/gateway.py
pushpull/websocket/server.py
pushpull-0.0.5.dist-info/DESCRIPTION.rst
pushpull-0.0.5.dist-info/METADATA
pushpull-0.0.5.dist-info/RECORD
pushpull-0.0.5.dist-info/WHEEL
pushpull-0.0.5.dist-info/entry_points.txt
pushpull-0.0.5.dist-info/metadata.json
pushpull-0.0.5.dist-info/top_level.txt
