Metadata-Version: 2.0
Name: pushpull
Version: 0.0.5
Summary: Websocket to message broker gateway
Home-page: https://github.com/elastic-coders/pushpull/
Author: Marco Paolini
Author-email: markopaolini@gmail.com
License: MIT
Keywords: websocket,asyncio,rabbitmq
Platform: UNKNOWN
Classifier: Development Status :: 4 - Beta
Classifier: Environment :: Console
Classifier: Environment :: Web Environment
Classifier: Intended Audience :: Developers
Classifier: License :: OSI Approved :: Apache Software License
Classifier: Intended Audience :: Developers
Classifier: Operating System :: POSIX :: Linux
Classifier: Programming Language :: Python
Classifier: Programming Language :: Python :: 3
Classifier: Programming Language :: Python :: 3.5
Classifier: Topic :: Internet :: WWW/HTTP
Classifier: Topic :: Software Development :: Libraries :: Python Modules
Requires-Dist: aioamqp (==0.7.0)
Requires-Dist: aiohttp (==0.22.5)
Requires-Dist: aiohttp-cors (==0.4.0)
Requires-Dist: click (==6.6)
